README.md
setup.cfg
setup.py
py_salus.egg-info/PKG-INFO
py_salus.egg-info/SOURCES.txt
py_salus.egg-info/dependency_links.txt
py_salus.egg-info/requires.txt
py_salus.egg-info/top_level.txt
salus/__init__.py
salus/api.py
salus/device.py
salus/device_readings.py